jupyterlab_diff/__init__.py
jupyterlab_diff/_version.py
jupyterlab_diff-0.6.1.data/data/share/jupyter/labextensions/jupyterlab-diff/package.json
jupyterlab_diff-0.6.1.data/data/share/jupyter/labextensions/jupyterlab-diff/static/299.07069b808cb23f84a242.js
jupyterlab_diff-0.6.1.data/data/share/jupyter/labextensions/jupyterlab-diff/static/379.2e2a6add1111d74422d2.js
jupyterlab_diff-0.6.1.data/data/share/jupyter/labextensions/jupyterlab-diff/static/383.dbd292b18614d410ed4b.js
jupyterlab_diff-0.6.1.data/data/share/jupyter/labextensions/jupyterlab-diff/static/499.e9c141febe62f251e965.js
jupyterlab_diff-0.6.1.data/data/share/jupyter/labextensions/jupyterlab-diff/static/680.07069b808cb23f84a242.js
jupyterlab_diff-0.6.1.data/data/share/jupyter/labextensions/jupyterlab-diff/static/728.559a28b17e14994cba46.js
jupyterlab_diff-0.6.1.data/data/share/jupyter/labextensions/jupyterlab-diff/static/747.e3256716cc1134700a59.js
jupyterlab_diff-0.6.1.data/data/share/jupyter/labextensions/jupyterlab-diff/static/879.749253139a5186f32109.js
jupyterlab_diff-0.6.1.data/data/share/jupyter/labextensions/jupyterlab-diff/static/remoteEntry.4830528fbe7c3ca55989.js
jupyterlab_diff-0.6.1.data/data/share/jupyter/labextensions/jupyterlab-diff/static/style.js
jupyterlab_diff-0.6.1.data/data/share/jupyter/labextensions/jupyterlab-diff/static/third-party-licenses.json
jupyterlab_diff-0.6.1.data/data/share/jupyter/labextensions/jupyterlab-diff/install.json
jupyterlab_diff-0.6.1.dist-info/METADATA
jupyterlab_diff-0.6.1.dist-info/WHEEL
jupyterlab_diff-0.6.1.dist-info/licenses/LICENSE
jupyterlab_diff-0.6.1.dist-info/RECORD
